hprof/__init__.py
hprof/_heap_parsing.py
hprof/_parsing.py
hprof/_special_cases.py
hprof/callstack.py
hprof/error.py
hprof/heap.py
hprof-0.1.0.dist-info/LICENSE
hprof-0.1.0.dist-info/WHEEL
hprof-0.1.0.dist-info/METADATA
hprof-0.1.0.dist-info/RECORD
