Metadata-Version: 2.1
Name: hprof
Version: 0.1.0
Summary: Analyse and explore .hprof heap dumps
License: MIT
Author: Snild Dolkow
Author-email: snild@dolkow.se
Requires-Python: >=3.6,<4.0
Classifier: License :: OSI Approved :: MIT License
Classifier: Programming Language :: Python :: 3
Classifier: Programming Language :: Python :: 3.10
Classifier: Programming Language :: Python :: 3.6
Classifier: Programming Language :: Python :: 3.7
Classifier: Programming Language :: Python :: 3.8
Classifier: Programming Language :: Python :: 3.9
